skyulf/__init__.py
skyulf/pipeline.py
skyulf/registry.py
skyulf/types.py
skyulf/utils.py
skyulf/core/meta/decorators.py
skyulf/data/__init__.py
skyulf/data/catalog.py
skyulf/data/dataset.py
skyulf/engines/__init__.py
skyulf/engines/pandas_engine.py
skyulf/engines/polars_engine.py
skyulf/engines/protocol.py
skyulf/engines/registry.py
skyulf/engines/sklearn_bridge.py
skyulf/modeling/__init__.py
skyulf/modeling/base.py
skyulf/modeling/classification.py
skyulf/modeling/cross_validation.py
skyulf/modeling/hyperparameters.py
skyulf/modeling/regression.py
skyulf/modeling/sklearn_wrapper.py
skyulf/modeling/evaluation/__init__.py
skyulf/modeling/evaluation/classification.py
skyulf/modeling/evaluation/common.py
skyulf/modeling/evaluation/metrics.py
skyulf/modeling/evaluation/regression.py
skyulf/modeling/evaluation/schemas.py
skyulf/modeling/tuning/__init__.py
skyulf/modeling/tuning/engine.py
skyulf/modeling/tuning/schemas.py
skyulf/preprocessing/__init__.py
skyulf/preprocessing/base.py
skyulf/preprocessing/bucketing.py
skyulf/preprocessing/casting.py
skyulf/preprocessing/cleaning.py
skyulf/preprocessing/dispatcher.py
skyulf/preprocessing/drop_and_missing.py
skyulf/preprocessing/encoding.py
skyulf/preprocessing/feature_generation.py
skyulf/preprocessing/feature_selection.py
skyulf/preprocessing/imputation.py
skyulf/preprocessing/inspection.py
skyulf/preprocessing/outliers.py
skyulf/preprocessing/pipeline.py
skyulf/preprocessing/resampling.py
skyulf/preprocessing/scaling.py
skyulf/preprocessing/split.py
skyulf/preprocessing/transformations.py
skyulf/profiling/__init__.py
skyulf/profiling/analyzer.py
skyulf/profiling/correlations.py
skyulf/profiling/distributions.py
skyulf/profiling/drift.py
skyulf/profiling/schemas.py
skyulf/profiling/visualizer.py
skyulf_core-0.1.10.dist-info/licenses/LICENSE
skyulf_core-0.1.10.dist-info/METADATA
skyulf_core-0.1.10.dist-info/WHEEL
skyulf_core-0.1.10.dist-info/top_level.txt
skyulf_core-0.1.10.dist-info/RECORD
