Metadata-Version: 2.4
Name: skyulf-core
Version: 0.1.10
Summary: The core machine learning library for Skyulf.
Author: Murat H. Unsal
Requires-Python: >=3.9
License-File: LICENSE
Requires-Dist: pandas>=2.0.0
Requires-Dist: numpy>=1.24.0
Requires-Dist: scikit-learn<2.0.0,>=1.4.0
Requires-Dist: polars>=0.19.0
Requires-Dist: imbalanced-learn>=0.13.0
Requires-Dist: pydantic>=2.0.0
Requires-Dist: optuna>=3.0.0
Requires-Dist: optuna-integration>=3.0.0
Requires-Dist: scipy>=1.10.0
Requires-Dist: statsmodels>=0.14.0
Provides-Extra: dev
Requires-Dist: pytest; extra == "dev"
Requires-Dist: twine; extra == "dev"
Requires-Dist: build; extra == "dev"
Provides-Extra: viz
Requires-Dist: matplotlib>=3.7.0; extra == "viz"
Requires-Dist: rich>=13.0.0; extra == "viz"
Dynamic: author
Dynamic: description
Dynamic: description-content-type
Dynamic: license-file
Dynamic: provides-extra
Dynamic: requires-dist
Dynamic: requires-python
Dynamic: summary
